LICENSE
MANIFEST.in
README.md
setup.cfg
setup.py
atmo_logger/__init__.py
atmo_logger/version.py
atmo_logger.egg-info/PKG-INFO
atmo_logger.egg-info/SOURCES.txt
atmo_logger.egg-info/dependency_links.txt
atmo_logger.egg-info/top_level.txt