Metadata-Version: 2.1
Name: atmo-logger
Version: 0.0.0
Summary: Logging for Atmosphere, modeled after threepio by jmatt.
Home-page: https://github.com/cyverse/atmo_logger
Author: cyverse
Author-email: atmodevs@gmail.com
License: The University of Arizona
Platform: UNKNOWN
Classifier: Development Status :: 4 - Beta
Classifier: Intended Audience :: Developers
Classifier: Intended Audience :: Information Technology
Classifier: License :: OSI Approved :: Apache Software License
Classifier: Operating System :: OS Independent
Classifier: Programming Language :: Python
Classifier: Topic :: Software Development :: Libraries
Classifier: Topic :: System :: Logging
